logger_es_handler/__init__.py
logger_es_handler/handlers.py
logger_es_handler/serializers.py
logger_es_handler-0.1.3.dist-info/LICENSE
logger_es_handler-0.1.3.dist-info/WHEEL
logger_es_handler-0.1.3.dist-info/METADATA
logger_es_handler-0.1.3.dist-info/RECORD
