Metadata-Version: 2.1
Name: logger-es-handler
Version: 0.1.3
Summary: ES handler for logging module 
Author: Gustavo Freitas
Author-email: gustavo@gmf-tech.com
Requires-Python: >=3.7,<4.0
Classifier: Programming Language :: Python :: 3
Classifier: Programming Language :: Python :: 3.7
Classifier: Programming Language :: Python :: 3.8
Classifier: Programming Language :: Python :: 3.9
Requires-Dist: elasticsearch (>=7.13.0,<8.0.0)
Requires-Dist: requests (>=2.25.1,<3.0.0)
Requires-Dist: requests-aws4auth (>=1.1.0,<2.0.0)
Requires-Dist: requests-kerberos (>=0.12.0,<0.13.0)
